mambo/__init__.py
mambo/cli.py
mambo/main.py
mambo/api/__init__.py
mambo/api/api.py
mambo/api/routers/admin_router.py
mambo/api/routers/general_router.py
mambo/api/routers/users_router.py
mambo/content/__init__.py
mambo/content/templates/__init__.py
mambo/content/templates/google/__init__.py
mambo/db/__init__.py
mambo/db/db_connection.py
mambo/db/declarative_base.py
mambo/db/security/admin_seeds.py
mambo/models/__init__.py
mambo/models/users_model.py
mambo/services/__init__.py
mambo/services/core_services.py
mambo/services/microservices/__init__.py
mambo/services/microservices/security_services.py
mambo/services/microservices/users_services.py
mambo/utils/__init__.py
mambo/utils/http/__init__.py
mambo/utils/http/response_utils.py
mamboframe-0.1.3.dist-info/licenses/LICENSE
mamboframe-0.1.3.dist-info/METADATA
mamboframe-0.1.3.dist-info/WHEEL
mamboframe-0.1.3.dist-info/entry_points.txt
mamboframe-0.1.3.dist-info/top_level.txt
mamboframe-0.1.3.dist-info/RECORD
