Metadata-Version: 2.4
Name: mamboframe
Version: 0.1.3
Summary: Plantilla backend con FastAPI
Author-email: Fernando Leguízamo <ferdhaban@gmail.com>
License-Expression: MIT
Requires-Python: >=3.10
License-File: LICENSE
Requires-Dist: fastapi[standard]==0.116.1
Requires-Dist: SQLAlchemy==2.0.43
Requires-Dist: python-dotenv==1.1.1
Requires-Dist: psycopg2-binary==2.9.10
Requires-Dist: passlib[bcrypt]==1.7.4
Requires-Dist: PyJWT==2.10.1
Requires-Dist: lxml==6.0.1
Requires-Dist: google-api-python-client==2.182.0
Requires-Dist: google-auth-httplib2==0.2.0
Requires-Dist: google-auth-oauthlib==1.2.2
Requires-Dist: google-genai==1.38.0
Requires-Dist: pydantic-settings==2.10.1
Dynamic: license-file
